{
    "name": "3D Print Price Calculator",
    "description": "A comprehensive tool for calculating 3D printing costs",
    "children": [
        {
            "name": "📱 Application Entry",
            "children": [
                {
                    "name": "index.html",
                    "description": "HTML entry point"
                },
                {
                    "name": "main.tsx",
                    "description": "React application bootstrap"
                },
                {
                    "name": "App.tsx",
                    "description": "Main app component with routing"
                }
            ]
        },
        {
            "name": "📄 Pages",
            "children": [
                {
                    "name": "Index.tsx",
                    "description": "Home page with calculator interface"
                },
                {
                    "name": "Settings.tsx",
                    "description": "Settings management page"
                },
                {
                    "name": "SavedQuotes.tsx",
                    "description": "View saved quotes page"
                },
                {
                    "name": "NotFound.tsx",
                    "description": "404 error page"
                }
            ]
        },
        {
            "name": "🧩 Components",
            "children": [
                {
                    "name": "Calculator Components",
                    "children": [
                        {
                            "name": "FDMCalculatorTable.tsx",
                            "description": "FDM printing calculator"
                        },
                        {
                            "name": "ResinCalculatorTable.tsx",
                            "description": "Resin printing calculator"
                        },
                        {
                            "name": "QuoteCalculator.tsx",
                            "description": "Quote calculation component"
                        },
                        {
                            "name": "FormField.tsx",
                            "description": "Reusable form field component"
                        },
                        {
                            "name": "ConsumablesSelector.tsx",
                            "description": "Consumables selection UI"
                        }
                    ]
                },
                {
                    "name": "File Upload",
                    "children": [
                        {
                            "name": "GcodeUpload.tsx",
                            "description": "G-code file upload for FDM"
                        },
                        {
                            "name": "ResinFileUpload.tsx",
                            "description": "Resin file upload (CTB, etc.)"
                        }
                    ]
                },
                {
                    "name": "Quote Components",
                    "children": [
                        {
                            "name": "QuoteSummary.tsx",
                            "description": "Quote summary display"
                        },
                        {
                            "name": "SavedQuotesTable.tsx",
                            "description": "Table of saved quotes"
                        }
                    ]
                },
                {
                    "name": "Settings Components",
                    "children": [
                        {
                            "name": "MaterialsManager.tsx",
                            "description": "Manage material presets"
                        },
                        {
                            "name": "MachinesManager.tsx",
                            "description": "Manage machine presets"
                        },
                        {
                            "name": "ConstantsManager.tsx",
                            "description": "Manage cost constants"
                        },
                        {
                            "name": "SettingsExportImport.tsx",
                            "description": "Export/import settings"
                        }
                    ]
                },
                {
                    "name": "Dashboard",
                    "children": [
                        {
                            "name": "QuotesDashboard.tsx",
                            "description": "Dashboard overview"
                        },
                        {
                            "name": "StatsCard.tsx",
                            "description": "Statistics card component"
                        }
                    ]
                },
                {
                    "name": "Shared/Common",
                    "children": [
                        {
                            "name": "CurrencyProvider.tsx",
                            "description": "Currency context provider"
                        },
                        {
                            "name": "CurrencySelector.tsx",
                            "description": "Currency selection dropdown"
                        },
                        {
                            "name": "Footer.tsx",
                            "description": "App footer component"
                        },
                        {
                            "name": "NavLink.tsx",
                            "description": "Navigation link component"
                        },
                        {
                            "name": "FeatureSuggestion.tsx",
                            "description": "Feature suggestion form"
                        },
                        {
                            "name": "ThumbnailPreview.tsx",
                            "description": "Thumbnail preview component"
                        }
                    ]
                },
                {
                    "name": "UI Components (49 total)",
                    "description": "Shadcn/UI component library",
                    "children": [
                        {
                            "name": "button.tsx",
                            "description": "Button component"
                        },
                        {
                            "name": "card.tsx",
                            "description": "Card component"
                        },
                        {
                            "name": "dialog.tsx",
                            "description": "Dialog/modal component"
                        },
                        {
                            "name": "form.tsx",
                            "description": "Form component"
                        },
                        {
                            "name": "input.tsx",
                            "description": "Input field component"
                        },
                        {
                            "name": "select.tsx",
                            "description": "Select dropdown component"
                        },
                        {
                            "name": "table.tsx",
                            "description": "Table component"
                        },
                        {
                            "name": "tabs.tsx",
                            "description": "Tabs component"
                        },
                        {
                            "name": "toast.tsx",
                            "description": "Toast notification"
                        },
                        {
                            "name": "... (40 more)",
                            "description": "Additional UI primitives"
                        }
                    ]
                }
            ]
        },
        {
            "name": "🎣 Hooks",
            "children": [
                {
                    "name": "useCalculatorData.ts",
                    "description": "Calculator data management hook"
                },
                {
                    "name": "useSavedQuotes.ts",
                    "description": "Saved quotes management hook"
                },
                {
                    "name": "use-toast.ts",
                    "description": "Toast notifications hook"
                },
                {
                    "name": "use-mobile.tsx",
                    "description": "Mobile detection hook"
                }
            ]
        },
        {
            "name": "📚 Library (lib)",
            "children": [
                {
                    "name": "gcodeParser.ts",
                    "description": "Parse G-code files for FDM data"
                },
                {
                    "name": "resinFileParser.ts",
                    "description": "Parse CTB/photon files for resin data"
                },
                {
                    "name": "quoteCalculations.ts",
                    "description": "Quote calculation logic"
                },
                {
                    "name": "pdfGenerator.ts",
                    "description": "Generate PDF quotes"
                },
                {
                    "name": "sessionStorage.ts",
                    "description": "Browser session storage utilities"
                },
                {
                    "name": "utils.ts",
                    "description": "General utility functions"
                }
            ]
        },
        {
            "name": "📝 Types",
            "children": [
                {
                    "name": "quote.ts",
                    "description": "Quote-related TypeScript types"
                }
            ]
        },
        {
            "name": "🖥️ Desktop (Electron)",
            "children": [
                {
                    "name": "main.cts",
                    "description": "Electron main process"
                },
                {
                    "name": "preload.cts",
                    "description": "Electron preload script"
                },
                {
                    "name": "tsconfig.json",
                    "description": "Electron TypeScript config"
                }
            ]
        },
        {
            "name": "📱 Mobile (Android/Capacitor)",
            "children": [
                {
                    "name": "capacitor.config.json",
                    "description": "Capacitor configuration"
                },
                {
                    "name": "android/",
                    "description": "Android native project"
                }
            ]
        },
        {
            "name": "⚙️ Configuration",
            "children": [
                {
                    "name": "vite.config.ts",
                    "description": "Vite build configuration"
                },
                {
                    "name": "tailwind.config.ts",
                    "description": "Tailwind CSS configuration"
                },
                {
                    "name": "tsconfig.json",
                    "description": "TypeScript configuration"
                },
                {
                    "name": "package.json",
                    "description": "NPM dependencies and scripts"
                },
                {
                    "name": "eslint.config.js",
                    "description": "ESLint configuration"
                },
                {
                    "name": "postcss.config.js",
                    "description": "PostCSS configuration"
                }
            ]
        }
    ]
}